web/dispatch/object/__init__.py
web/dispatch/object/dispatch.py
web/dispatch/object/release.py
web/dispatch/object/__pycache__/__init__.cpython-37.opt-1.pyc
web/dispatch/object/__pycache__/dispatch.cpython-37.opt-1.pyc
web/dispatch/object/__pycache__/release.cpython-37.opt-1.pyc
web.dispatch.object-3.0.0.dist-info/LICENSE.txt
web.dispatch.object-3.0.0.dist-info/METADATA
web.dispatch.object-3.0.0.dist-info/WHEEL
web.dispatch.object-3.0.0.dist-info/entry_points.txt
web.dispatch.object-3.0.0.dist-info/top_level.txt
web.dispatch.object-3.0.0.dist-info/RECORD
