Metadata-Version: 2.1
Name: web.dispatch.object
Version: 3.0.0
Summary: Object dispatch; a method to resolve path components to Python objects using directed attribute access.
Home-page: https://github.com/marrow/web.dispatch.object
Author: Alice Bevan-McGregor
Author-email: alice@gothcandy.com
License: MIT
Download-URL: https://pypi.org/project/web.dispatch.object/releases
Project-URL: Repository, https://github.com/marrow/web.dispatch.object/
Project-URL: Documentation, https://github.com/marrow/web.dispatch.object/#readme
Project-URL: Issue Tracker, https://github.com/marrow/web.dispatch.object/issues
Project-URL: Funding, https://www.patreon.com/GothAlice
Keywords: marrow,dispatch,web.dispatch,object dispatch,endpoint discovery,WebCore
Platform: UNKNOWN
Classifier: Development Status :: 5 - Production/Stable
Classifier: Environment :: Console
Classifier: Environment :: Web Environment
Classifier: Intended Audience :: Developers
Classifier: License :: OSI Approved :: MIT License
Classifier: Operating System :: OS Independent
Classifier: Programming Language :: Python
Classifier: Programming Language :: Python :: 3
Classifier: Programming Language :: Python :: 3.6
Classifier: Programming Language :: Python :: 3.7
Classifier: Programming Language :: Python :: 3.8
Classifier: Programming Language :: Python :: Implementation :: CPython
Classifier: Programming Language :: Python :: Implementation :: PyPy
Classifier: Topic :: Software Development :: Libraries :: Python Modules
Requires-Python: ~=3.6
Requires-Dist: web.dispatch (~=3.0.1)
Provides-Extra: development
Requires-Dist: pytest ; extra == 'development'
Requires-Dist: pytest-cov ; extra == 'development'
Requires-Dist: pytest-flakes ; extra == 'development'
Requires-Dist: pytest-isort ; extra == 'development'
Requires-Dist: pre-commit ; extra == 'development'
